odoo/addons/partner_contact_role/README.rst
odoo/addons/partner_contact_role/__init__.py
odoo/addons/partner_contact_role/__manifest__.py
odoo/addons/partner_contact_role/i18n/partner_contact_role.pot
odoo/addons/partner_contact_role/models/__init__.py
odoo/addons/partner_contact_role/models/res_partner.py
odoo/addons/partner_contact_role/security/ir.model.access.csv
odoo/addons/partner_contact_role/static/description/icon.png
odoo/addons/partner_contact_role/views/res_partner.xml
odoo/addons/partner_contact_role/views/res_partner_role.xml
odoo11_addon_partner_contact_role-11.0.1.0.0.99.dev1.dist-info/METADATA
odoo11_addon_partner_contact_role-11.0.1.0.0.99.dev1.dist-info/WHEEL
odoo11_addon_partner_contact_role-11.0.1.0.0.99.dev1.dist-info/top_level.txt
odoo11_addon_partner_contact_role-11.0.1.0.0.99.dev1.dist-info/RECORD
